{
  "schemaVersion": 1,
  "poolVersion": "v1",
  "dailyId": "2026-05-01",
  "dailySlot": 7902,
  "canonicalKey": "8a0718182bba867588c23afa84363867",
  "generatedAtUtcMs": 1777593601000,
  "hardInvalidateAtUtcMs": 1777680000000,
  "level": {
    "name": "Daily 2026-05-01",
    "grid": [
      "..##..",
      "..#...",
      "......",
      "..h.t.",
      "......"
    ],
    "stitches": [
      [
        1,
        1
      ],
      [
        2,
        4
      ]
    ],
    "cornerCounts": [
      [
        1,
        5,
        2
      ]
    ]
  }
}
