{
  "schemaVersion": 1,
  "poolVersion": "v1",
  "dailyId": "2026-03-19",
  "dailySlot": 10468,
  "canonicalKey": "739196971142e57622ce298f79d6fe64",
  "generatedAtUtcMs": 1773878401000,
  "hardInvalidateAtUtcMs": 1773964800000,
  "level": {
    "name": "Daily 2026-03-19",
    "grid": [
      "l..s..",
      "...##.",
      "...#..",
      "......",
      "......",
      ".....l"
    ],
    "stitches": [],
    "cornerCounts": [
      [
        5,
        2,
        3
      ],
      [
        5,
        3,
        1
      ]
    ]
  }
}
